AGTEPyth/AGTPytGD.py
AGTEPyth/DataResource_rc.py
AGTEPyth/Functions.py
AGTEPyth/PRINT_RESULST_TO_DOCX.py
AGTEPyth/__init__.py
AGTEPyth/inputData.py
AGTEPyth-0.0.6.dist-info/LICENSE
AGTEPyth-0.0.6.dist-info/METADATA
AGTEPyth-0.0.6.dist-info/WHEEL
AGTEPyth-0.0.6.dist-info/top_level.txt
AGTEPyth-0.0.6.dist-info/RECORD
