Metadata-Version: 2.1
Name: AGTEPyth
Version: 0.0.6
Summary: A sample python package to start sharing your code with the world
Home-page: https://github.com/PhamThanhQuyet/AGTEPyth
Author: Pham Thanh Quyet
Author-email: phamthanhquyet.kcd@gmail.com
Requires-Python: >=3.10
License-File: LICENSE
Requires-Dist: pandas
Requires-Dist: numpy
Requires-Dist: matplotlib
Requires-Dist: pyqt5
Requires-Dist: python-docx
